[
  {
    "key": "nco-0001-book",
    "traductions": {
      "SPA": [],
      "ENG": [
        "eng-nco-0001-book"
      ],
      "POL": [
        "pol-nco-0001-książka"
      ]
    },
    "papers": [
      "concrete",
      "household object",
      "s2"
    ],
    "topics": [
      "bedroom",
      "home",
      "inside",
      "school"
    ]
  },
  {
    "key": "nco-0002-spoon",
    "traductions": {
      "SPA": [],
      "ENG": [
        "eng-nco-0002-spoon"
      ],
      "POL": [
        "pol-nco-0002-łyżka"
      ]
    },
    "papers": [
      "concrete",
      "eating utensil",
      "household object",
      "s1"
    ],
    "topics": [
      "kitchen",
      "home",
      "inside"
    ]
  },
  {
    "key": "nco-0003-glass(tumbler)",
    "traductions": {
      "SPA": [],
      "ENG": [
        "eng-nco-0003-glass(tumbler)"
      ],
      "POL": [
        "pol-nco-0003-szklanka"
      ]
    },
    "papers": [
      "container",
      "concrete",
      "household object",
      "s2"
    ],
    "topics": [
      "kitchen",
      "home",
      "inside"
    ]
  },
  {
    "key": "nco-0004-spring",
    "traductions": {
      "SPA": [],
      "ENG": [
        "eng-nco-0005-spring"
      ],
      "POL": [
        "pol-nco-0004-wiosna"
      ]
    },
    "papers": [
      "abstract"
    ],
    "topics": [
      "time"
    ]
  },
  {
    "key": "nco-0005-onion",
    "traductions": {
      "SPA": [],
      "ENG": [
        "eng-nco-0006-onion"
      ],
      "POL": [
        "pol-nco-0005-cebula"
      ]
    },
    "papers": [
      "food",
      "concrete",
      "vegetable",
      "s1"
    ],
    "topics": [
      "kitchen",
      "inside",
      "restaurant"
    ]
  },
  {
    "key": "nco-0006-tea",
    "traductions": {
      "SPA": [],
      "ENG": [
        "eng-nco-0007-tea"
      ],
      "POL": [
        "pol-nco-0006-herbata"
      ]
    },
    "papers": [
      "drink",
      "concrete",
      "s2"
    ],
    "topics": [
      "kitchen",
      "inside",
      "restaurant"
    ]
  }
]