[
    {
        "lemma": "wstawać",
        "tags": "v,bb4",
        "translations": {
            "ENG": [
                "to get up[i]",
                "to stand up[i]"
            ]
        },
        "temp_id": "1.1"
    },
    {
        "lemma": "zjeść",
        "tags": "bb,f,coo1",
        "translations": {
            "ENG": [
                "to eat"
            ]
        },
        "temp_id": "1.2"
    },
    {
        "lemma": "przychodzić",
        "tags": "xxxxxxxxx",
        "translations": {
            "ENG": [
                "to arrive[i]","to come[i]"
            ]
        },
        "temp_id": "1.3"
    },
    {
        "lemma": "brać",
        "tags": "v,bb,sg2",
        "translations": {
            "ENG": [
                "to take"
            ]
        },
        "temp_id": "1.4"
    },
    {
        "lemma": "biec",
        "tags": "3yy,bb,v",
        "translations": {
            "ENG": [
"to run[i]"            ]
        },
        "temp_id": "1.5"
    },
    {
        "lemma": "siedzieć",
        "tags": "2bb,s",
        "translations": {
            "ENG": [
"to sit[i]"            ]
        },
        "temp_id": "1.6"
    },
    {
        "lemma": "siadać",
        "tags": "2bb,s",
        "translations": {
            "ENG": [
                "to sit down[i]",
                "( intransitive ) of animals or airplains to land",
                "( intransitive colloquial ) to go sour , to go downhill"
            ]
        },
        "temp_id": "1.7"
    },
    {
        "lemma": "stawać",
        "tags": "4aa",
        "translations": {
            "ENG": [
                "to become[r]"
            ]
        },
        "temp_id": "1.9"
    },
    {
        "lemma": "wstać",
        "tags": "v,bb4",
        "translations": {
            "ENG": [
                "to get up[i]",
                "to stand up[i]"
            ]
        },
        "temp_id": "1.10"
    },
    {
        "lemma": "przyjechać",
        "tags": "3v,ŧŧ",
        "translations": {
            "ENG": [
                "to arrive[i]"
            ]
        },
        "temp_id": "1.11"
    },
    {
        "lemma": "upadać",
        "tags": "4v",
        "translations": {
            "ENG": [
                "to fall down[i]","to drop[i]"]
        },
        "temp_id": "1.12"
    },
    {
        "lemma": "przynosić",
        "tags": "3v,sg",
        "translations": {
            "ENG": [
                "to bring","to fetch"
            ]
        },
        "temp_id": "1.13"
    },
    {
        "lemma": "zanieść",
        "tags": "4sg,v,bb",
        "translations": {
            "ENG": [
                "to carry"
            ]
        },
        "temp_id": "1.14"
    },
    {
        "lemma": "przygotowywać",
        "tags": "4coo,pl",
        "translations": {
            "ENG": [
                "to prepare"
            ]
        },
        "temp_id": "1.15"
    },
    {
        "lemma": "włożyć",
        "tags": "3v,ag",
        "translations": {
            "ENG": [
                "to put in",
                "to put inside"
            ]
        },
        "temp_id": "1.16"
    },
    {
        "lemma": "usiąść",
        "tags": "2bb,s",
        "translations": {
            "ENG": [
                "to sit down[i]"
            ]
        },
        "temp_id": "1.17"
    },
    {
        "lemma": "zmienić",
        "tags": "2",
        "translations": {
            "ENG": [
                "to change","to modify","to replace"
            ]
        },
        "temp_id": "1.18"
    },
    {
        "lemma": "liczyć",
        "tags": "3mat,s",
        "translations": {
            "ENG": [
                "to count","to count on","to matter"
            ]
        },
        "temp_id": "1.19"
    },
    {
        "lemma": "dawać",
        "tags": "2sg,rp",
        "translations": {
            "ENG": [
                "to give","to let","to allow","to permit"
            ]
        },
        "temp_id": "1.20"
    },
    {
        "lemma": "wracać",
        "tags": "3v,ŧŧ",
        "translations": {
            "ENG": [
                "to return[i]","to come back[i]"
            ]
        },
        "temp_id": "1.21"
    },
    {
        "lemma": "woleć",
        "tags": "2ee",
        "translations": {
            "ENG": [
                "to prefer[i]"
            ]
        },
        "temp_id": "1.22"
    },
    {
        "lemma": "wziąć",
        "tags": "v,bb,sg2",
        "translations": {
            "ENG": [
                "to take"
            ]
        },
        "temp_id": "1.23"
    },
    {
        "lemma": "zmieniać",
        "tags": "2",
        "translations": {
            "ENG": [
                "to change","to modify","to replace"
            ]
        },
        "temp_id": "1.24"
    },
    {
        "lemma": "!dziać",
        "tags": "xxxxxxxxx",
        "translations": {
            "ENG": [
                "( transitive ) to knit"
            ]
        },
        "temp_id": "1.25"
    },
    {
        "lemma": "dziać",
        "tags": "4aa,pl",
        "translations": {
            "ENG": [
                "to happen[r]"
            ]
        },
        "temp_id": "1.26"
    },
    {
        "lemma": "biegać",
        "tags": "3yy,bb",
        "translations": {
            "ENG": [
                "to run[i]",
                "to jog[i]"
            ]
        },
        "temp_id": "1.27"
    },
    {
        "lemma": "jeść",
        "tags": "bb,f,coo1",
        "translations": {
            "ENG": [
                "to eat[t]",
                "to eat[i]"
            ]
        },
        "temp_id": "1.28"
    },
    {
        "lemma": "umieć",
        "tags": "xxxxxxxxx",
        "translations": {
            "ENG": [
                "( transitive ) to know , to be able to , to know how (to do), can (have learnt)"
            ]
        },
        "temp_id": "1.29"
    },
    {
        "lemma": "upaść",
        "tags": "xxxxxxxxx",
        "translations": {
            "ENG": [
                "to fall , to drop",
                "( figuratively ) to fall down , to abruptly deteriorate"
            ]
        },
        "temp_id": "1.30"
    },
    {
        "lemma": "upaść",
        "tags": "xxxxxxxxx",
        "translations": {
            "ENG": [
                "to complete fattening an animal, so that it is ready for slaughter"
            ]
        },
        "temp_id": "1.31"
    },
    {
        "lemma": "wrócić",
        "tags": "xxxxxxxxx",
        "translations": {
            "ENG": [
                "( intransitive ) to return , to get back , to come back Synonym: powrócić",
                "( transitive ) to restore give back Synonym: zwrócić przywrócić",
                "( reflexive ) to return , to get back , to come back Synonym: powrócić"
            ]
        },
        "temp_id": "1.32"
    },
    {
        "lemma": "być",
        "tags": "xxxxxxxxx",
        "translations": {
            "ENG": [
                "( intransitive ) to be ( indicates sameness or membership in a class ) [+nominative or instrumental]",
                "( intransitive ) to be ( auxilary verb used for predication ) [+adjective] Jestem zmęczona. ― I am tired.",
                "( intransitive ) In future tense, forms future tense of imperfective verbs. [+infinitive or verb in past tense]",
                "( archaic intransitive ) In past tense, forms pluperfect tense. [+verb in past tense] 1859 , Jean Jacques Rapet, Przewodnik moralności i ekonomii-politycznej dla użytku klass roboczych , Behr Bock, page 170 Gdybyś naprzykład, panie Rawski, był zjadł wszystko coś zarobił, to byś nie był zebrał majątku. If you for example, Mr Rawski, had eaten everything that you earned, then you would not have collected a fortune.",
                "1869 , Charles Edmond (translated by Edmund Chojecki), Alkhadar: uste̜p z dziejów ojców naszych , F.A. Brockhaus, page 231 Nastusia na pół osunięta, na pół wsparta na dębie, na pół omdlała, z oczyma szeroko, nieruchomie otwartemi, utkwionemi w stronę, gdzie jastrząb dokonał był pomyślnych swoich łowów, strasznie dyszała. Nastusia, half-fallen, half-supported by the oak, with her eyes opened wide in a motionless manner, fixed in the direction where the hawk had successfully carried out its hunts, was panting terribly.",
                "1871 , Czesław Pieniążek, Włościanin: czasopismo ilustrowane dla ludu , Budweiser, page 34 Ale cóż, gdyby był poszedł tam w to miejsce, jakie przystało honorowi i jego osobie, toby był musiał co dzień kilka i kilkanaście złotych wydać; to cóż on robił? Oh well, if he had gone there into that place, as befitted his honour and his person, then he would have had to spend a few and a few dozen złoty; so what did he do?",
                "( intransitive ) to be ( indicates location ) there be Antonym: nie ma"
            ]
        },
        "temp_id": "1.33"
    },
    {
        "lemma": "móc",
        "tags": "xxxxxxxxx",
        "translations": {
            "ENG": [
                "( intransitive ) to be able may might",
                "( intransitive ) to be allowed"
            ]
        },
        "temp_id": "1.34"
    },
    {
        "lemma": "chcieć",
        "tags": "xxxxxxxxx",
        "translations": {
            "ENG": [
                "( transitive ) to want"
            ]
        },
        "temp_id": "1.35"
    },
    {
        "lemma": "wypić",
        "tags": "xxxxxxxxx",
        "translations": {
            "ENG": [
                "( transitive ) to drink a portion of fluid (e.g. a cup of coffee; a can of beer) wholly Synonyms: see Thesaurus: pić"
            ]
        },
        "temp_id": "1.36"
    },
    {
        "lemma": "przynieść",
        "tags": "xxxxxxxxx",
        "translations": {
            "ENG": [
                "( transitive ) to bring , to fetch",
                "( transitive ) to bring on , to occasion , to cause",
                "( transitive ) to print , to publish"
            ]
        },
        "temp_id": "1.37"
    },
    {
        "lemma": "przyjeżdżać",
        "tags": "xxxxxxxxx",
        "translations": {
            "ENG": [
                "( intransitive ) to arrive , to pull in (in a vehicle)"
            ]
        },
        "temp_id": "1.38"
    },
    {
        "lemma": "przygotować",
        "tags": "xxxxxxxxx",
        "translations": {
            "ENG": [
                "( transitive ) to prepare"
            ]
        },
        "temp_id": "1.39"
    },
    {
        "lemma": "policzyć",
        "tags": "xxxxxxxxx",
        "translations": {
            "ENG": [
                "( intransitive ) to count ( recite numbers in sequence )",
                "( transitive ) to count , to enumerate ( determine the amount of something )",
                "( reflexive ) to get even , to even the score"
            ]
        },
        "temp_id": "1.40"
    },
    {
        "lemma": "ugotować",
        "tags": "xxxxxxxxx",
        "translations": {
            "ENG": [
                "( transitive ) to cook ( prepare food for eating )",
                "( transitive ) to boil ( heat to boiling temperature )",
                "( reflexive ) to boil , to seethe ( be at boiling temperature )",
                "( reflexive figuratively ) to seethe , to fume ( be in an agitated or angry mental state )"
            ]
        },
        "temp_id": "1.41"
    },
    {
        "lemma": "pić",
        "tags": "xxxxxxxxx",
        "translations": {
            "ENG": [
                "( transitive intransitive ) to drink (liquid)",
                "( transitive intransitive ) to drink (alcohol)",
                "( intransitive ) to hint , to insinuate , to allude maliciously Dlaczego pijesz do mnie ? ― Why are you alluding to me? Synonyms: przymawiać przycinać",
                "( transitive ) to pinch ( of clothes or shoes ) Synonyms: uwierać uciskać gnieść ugniatać"
            ]
        },
        "temp_id": "1.42"
    },
    {
        "lemma": "mieć",
        "tags": "xxxxxxxxx",
        "translations": {
            "ENG": [
                "( intransitive ) to have Mam kota. ― I have a cat.",
                "( intransitive ) to be (for an age) Mam 22 lata. ― I am 22 [years old]. (literally I have 22 years. )",
                "( auxiliary intransitive ) must have to need to supposed to Mamy iść na zakupy. ― We have to go shopping.",
                "( intransitive ) to feel something",
                "( reflexive ) to fare (to be in any state, or pass through any experience, good or bad)",
                "( reflexive ) to consider oneself Masz się za lepszego? ― You think you're better than me?",
                "( intransitive impersonal strictly in the negative ) to be gone , to not be present there is no . Antonym: być"
            ]
        },
        "temp_id": "1.43"
    },
    {
        "lemma": "gotować",
        "tags": "xxxxxxxxx",
        "translations": {
            "ENG": [
                "( transitive ) to cook ( prepare food for eating )",
                "( transitive ) to boil ( heat to boiling temperature )",
                "( reflexive ) to boil , to seethe ( be at boiling temperature )",
                "( reflexive figuratively ) to seethe , to fume ( be in an agitated or angry mental state )"
            ]
        },
        "temp_id": "1.44"
    },
    {
        "lemma": "stać",
        "tags": "xxxxxxxxx",
        "translations": {
            "ENG": [
                "( reflexive ) to become Myślisz, że się zmieni, gdy stanie się sławna? ― Do you think she will change when she becomes famous? Po kilku dniach stali się najlepszymi przyjaciółmi. ― After a few days, they became best friends. Jego twarz stała się czerwona ze złości. ― His face turned red with anger."
            ]
        },
        "temp_id": "1.45"
    },
    {
        "lemma": "stać",
        "tags": "xxxxxxxxx",
        "translations": {
            "ENG": [
                "( intransitive ) to stand (to remain motionless in a vertical position) Dlaczego ci ludzie tu stoją ? ― Why are these people standing here? Stała przed nim przez pięć minut. ― She stood in front of him for five minutes.",
                "( intransitive ) to be (about position of the object) Te książki wcześniej stały na półce. ― These books were previously on the shelf. Na przystanku stoi autobus. ― There is a bus at the stop. Stała w korku przez pięć minut. ― She was in traffic for five minutes.",
                "( intransitive ) to stop (about not working mechanism) Zegarek stał , a ja nie mogłem go naprawić. ― The watch wasn't working and I couldn't fix it.",
                "( intransitive ) to stagnate Od kilku miesięcy gospodarka stoi w miejscu . ― The economy has been in stagnation for several months now."
            ]
        },
        "temp_id": "1.46"
    },
    {
        "lemma": "schodzić",
        "tags": "xxxxxxxxx",
        "translations": {
            "ENG": [
                "( intransitive colloquial especially of shoes ) to wear out",
                "( reflexive ) to walk a long distance Synonym: zleźć się"
            ]
        },
        "temp_id": "1.48"
    },
    {
        "lemma": "musieć",
        "tags": "xxxxxxxxx",
        "translations": {
            "ENG": [
                "( intransitive ) to have to , to need to, to be obliged to Musimy porozmawiać. ― We need to talk. Musiałem coś zjeść. ― I had to eat something.",
                "( intransitive ) must Muszę iść. ― I must go."
            ]
        },
        "temp_id": "1.49"
    },
    {
        "lemma": "wkładać",
        "tags": "xxxxxxxxx",
        "translations": {
            "ENG": [
                "( transitive ) to put in (to place inside something)"
            ]
        },
        "temp_id": "1.50"
    },
    {
        "lemma": "dać",
        "tags": "xxxxxxxxx",
        "translations": {
            "ENG": [
                "( transitive ) to give Dałeś dzieciom obiad? ― Did you give lunch to the children?",
                "( intransitive ) to let ; to allow ; to permit Daj mi posłuchać. ― Let me listen.",
                "( intransitive vulgar ) to put out ; to consent to sex (used mainly of women) Jak było u niego? Dałaś mu? ― How was it at his place? Did you put out ?",
                "( reflexive ) to give in ; to let go",
                "( reflexive ) to be feasible"
            ]
        },
        "temp_id": "1.51"
    },
    {
        "lemma": "przyjść",
        "tags": "xxxxxxxxx",
        "translations": {
            "ENG": [
                "( intransitive ) to arrive , to come"
            ]
        },
        "temp_id": "1.52"
    },
    {
        "lemma": "zjadać",
        "tags": "xxxxxxxxx",
        "translations": {
            "ENG": [
                "( transitive ) to eat up"
            ]
        },
        "temp_id": "1.53"
    },
    {
        "lemma": "jadać",
        "tags": "xxxxxxxxx",
        "translations": {
            "ENG": [
                "( transitive ) to eat habitually Jadałem tam, kiedy byłem studentem. ― I used to eat there when I was a student."
            ]
        },
        "temp_id": "1.54"
    },
    {
        "lemma": "pobiec",
        "tags": "xxxxxxxxx",
        "translations": {
            "ENG": [
                "( intransitive ) to run forward",
                "( intransitive colloquial ) to nip , to dash ( make a quick journey )",
                "( intransitive literary of thoughts, glances, etc. ) to turn , to wander"
            ]
        },
        "temp_id": "1.55"
    },
    {
        "lemma": "posiedzieć",
        "tags": "xxxxxxxxx",
        "translations": {
            "ENG": [
                "( intransitive ) to sit for a while"
            ]
        },
        "temp_id": "1.56"
    },
    {
        "lemma": "siąść",
        "tags": "xxxxxxxxx",
        "translations": {
            "ENG": [
                "( intransitive ) to sit down Synonym: usiąść",
                "( intransitive of animals or airplanes ) to land",
                "( intransitive colloquial ) to go sour , to go downhill"
            ]
        },
        "temp_id": "1.57"
    },
    {
        "lemma": "stanąć",
        "tags": "xxxxxxxxx",
        "translations": {
            "ENG": [
                "( intransitive ) to stand Nie mogę się doczekać, kiedy stanę na szczycie tej góry. ― I can't wait to stand on the summit of that mountain. Stańcie tutaj i się nie ruszajcie! ― Stand here and don't move!",
                "( intransitive ) to stop Maszyna zaskrzypiała i stanęła . ― The machine squeaked and stopped .",
                "( intransitive ) to park Stanęliśmy pod sklepem. ― We parked next to the store.",
                "( intransitive ) to step , to step on [+ na (object) = on something] Uważaj, żeby nie stanąć na luźnej desce. ― Watch out so you don't step on a loose board. Zobacz czy podłoga jest czysta, zanim na niej staniesz . ― See if floor is clean before stepping on it.",
                "( intransitive colloquial ) to become erect Już ci stanął ? ― You are already hard?"
            ]
        },
        "temp_id": "1.58"
    },
    {
        "lemma": "zanosić",
        "tags": "xxxxxxxxx",
        "translations": {
            "ENG": [
                "( transitive ) to carry , to transport by carrying",
                "( reflexive ) to be in the air , to look like"
            ]
        },
        "temp_id": "1.59"
    },
    {
        "lemma": "pobiec",
        "tags": "xxxxxxxxx",
        "translations": {
            "ENG": [
                "( intransitive ) to run forward",
                "( intransitive colloquial ) to nip , to dash ( make a quick journey )",
                "( intransitive literary of thoughts, glances, etc. ) to turn , to wander"
            ]
        },
        "temp_id": "1.60"
    },
    {
        "lemma": "jadać",
        "tags": "xxxxxxxxx",
        "translations": {
            "ENG": [
                "( transitive ) to eat habitually Jadałem tam, kiedy byłem studentem. ― I used to eat there when I was a student."
            ]
        },
        "temp_id": "1.61"
    },
    {
        "lemma": "bywać",
        "tags": "xxxxxxxxx",
        "translations": {
            "ENG": [
                "( intransitive ) to be once in a while; to appear , to frequent , to happen (to be) On bywa całkiem wredny. ― He can be pretty mean."
            ]
        },
        "temp_id": "1.62"
    },
    {
        "lemma": "wypijać",
        "tags": "xxxxxxxxx",
        "translations": {
            "ENG": [
                "( transitive ) to drink up , to drink Synonyms: see Thesaurus: pić"
            ]
        },
        "temp_id": "1.63"
    },
    {
        "lemma": "miewać",
        "tags": "xxxxxxxxx",
        "translations": {
            "ENG": [
                "( intransitive ) to have something repeatedly; to have a tendency for something W dzieciństwie miewałem częste bóle głowy. ― As a child, I used to have frequent headaches.",
                "( reflexive ) to fare (to be in any state, or pass through any experience, good or bad)"
            ]
        },
        "temp_id": "1.64"
    },
    {
        "lemma": "stanąć",
        "tags": "xxxxxxxxx",
        "translations": {
            "ENG": [
                "( intransitive ) to stand Nie mogę się doczekać, kiedy stanę na szczycie tej góry. ― I can't wait to stand on the summit of that mountain. Stańcie tutaj i się nie ruszajcie! ― Stand here and don't move!",
                "( intransitive ) to stop Maszyna zaskrzypiała i stanęła . ― The machine squeaked and stopped .",
                "( intransitive ) to park Stanęliśmy pod sklepem. ― We parked next to the store.",
                "( intransitive ) to step , to step on [+ na (object) = on something] Uważaj, żeby nie stanąć na luźnej desce. ― Watch out so you don't step on a loose board. Zobacz czy podłoga jest czysta, zanim na niej staniesz . ― See if floor is clean before stepping on it.",
                "( intransitive colloquial ) to become erect Już ci stanął ? ― You are already hard?"
            ]
        },
        "temp_id": "1.65"
    },
    {
        "lemma": "zejść",
        "tags": "xxxxxxxxx",
        "translations": {
            "ENG": [
                "( intransitive ) to descend , to go down Synonym: zleźć",
                "( intransitive ) to depreciate , to decrease in value",
                "( intransitive ) to give way",
                "( intransitive euphemistic ) to die",
                "( intransitive colloquial ) to shift , to sell quickly",
                "( intransitive colloquial of a stain ) to come out",
                "( reflexive ) to descend , to converge , to gather Synonym: zleźć",
                "( reflexive ) to get back together"
            ]
        },
        "temp_id": "1.66"
    }
]